odoo/addons/sale_commission_geo_assign/README.rst
odoo/addons/sale_commission_geo_assign/__init__.py
odoo/addons/sale_commission_geo_assign/__manifest__.py
odoo/addons/sale_commission_geo_assign/i18n/es.po
odoo/addons/sale_commission_geo_assign/i18n/it.po
odoo/addons/sale_commission_geo_assign/i18n/sale_commission_geo_assign.pot
odoo/addons/sale_commission_geo_assign/models/__init__.py
odoo/addons/sale_commission_geo_assign/models/res_partner.py
odoo/addons/sale_commission_geo_assign/readme/CONFIGURE.rst
odoo/addons/sale_commission_geo_assign/readme/CONTRIBUTORS.rst
odoo/addons/sale_commission_geo_assign/readme/DESCRIPTION.rst
odoo/addons/sale_commission_geo_assign/readme/USAGE.rst
odoo/addons/sale_commission_geo_assign/security/ir.model.access.csv
odoo/addons/sale_commission_geo_assign/static/description/icon.png
odoo/addons/sale_commission_geo_assign/static/description/index.html
odoo/addons/sale_commission_geo_assign/tests/__init__.py
odoo/addons/sale_commission_geo_assign/tests/test_sale_commission_geo_assign.py
odoo/addons/sale_commission_geo_assign/views/res_partner_view.xml
odoo/addons/sale_commission_geo_assign/wizard/__init__.py
odoo/addons/sale_commission_geo_assign/wizard/wizard_geo_assign_partner.py
odoo/addons/sale_commission_geo_assign/wizard/wizard_geo_assign_partner_view.xml
odoo14_addon_sale_commission_geo_assign-14.0.1.1.3.dist-info/METADATA
odoo14_addon_sale_commission_geo_assign-14.0.1.1.3.dist-info/WHEEL
odoo14_addon_sale_commission_geo_assign-14.0.1.1.3.dist-info/top_level.txt
odoo14_addon_sale_commission_geo_assign-14.0.1.1.3.dist-info/RECORD
